<launch>
  <!-- Input -->
  <arg name="input/data" default="~/input/data" />

  <!-- Output -->
  <arg name="output/data" default="~/output/data" />

  <!-- Parameter -->
  <arg name="config_file" default="$(find-pkg-share radar_threshold_filter)/config/radar_threshold_filter.param.yaml" />
  <arg name="update_rate_hz" default="10.0" />

  <!-- Node -->
  <node pkg="radar_threshold_filter" exec="radar_threshold_filter_node" name="radar_threshold_filter" output="screen">
    <!-- Input -->
    <remap from="~/input/data" to="$(var input/data)"/>

    <!-- Output -->
    <remap from="~/output/data" to="$(var output/data)"/>

    <!-- Parameter -->
    <param from="$(var config_file)" />
    <param name="update_rate_hz" value="$(var update_rate_hz)"/>
  </node>
</launch>
